very_good_setuptools_git_version.py
very_good_setuptools_git_version-1.0.8.dist-info/METADATA
very_good_setuptools_git_version-1.0.8.dist-info/RECORD
very_good_setuptools_git_version-1.0.8.dist-info/WHEEL
very_good_setuptools_git_version-1.0.8.dist-info/entry_points.txt
very_good_setuptools_git_version-1.0.8.dist-info/top_level.txt
