Metadata-Version: 2.1
Name: very-good-setuptools-git-version
Version: 1.0.8
Summary: Automatically set package version from Git.
Home-page: https://github.com/Kautenja/very-good-setuptools-git-version
Author: Chritian Kauten
Author-email: kautencreations@gmail.com
License: MIT
Keywords: setuptools git version-control
Platform: UNKNOWN
Classifier: Framework :: Setuptools Plugin
Classifier: Intended Audience :: Developers
Classifier: License :: OSI Approved :: MIT License
Classifier: Programming Language :: Python :: 2
Classifier: Programming Language :: Python :: 3
Classifier: Development Status :: 5 - Production/Stable
Requires-Dist: setuptools (>=8.0)
